comfyui_utils/__init__.py
comfyui_utils/comfy.py
comfyui_utils/gen_prompts.py
comfyui_utils/test_gen_prompts.py
examples/__init__.py
examples/e2e.py
comfyui_utils-0.0.1.dist-info/METADATA
comfyui_utils-0.0.1.dist-info/WHEEL
comfyui_utils-0.0.1.dist-info/entry_points.txt
comfyui_utils-0.0.1.dist-info/top_level.txt
comfyui_utils-0.0.1.dist-info/RECORD
