Metadata-Version: 2.1
Name: comfyui-utils
Version: 0.0.1
Summary: Utilities for working with the ComfyUI API.
Author-email: Andrey Ryabtsev <ryabtsev.code@gmail.com>
Project-URL: Homepage, https://github.com/andreyryabtsev/comfyui_utils
Keywords: comfyui,api
Classifier: License :: OSI Approved :: MIT License
Classifier: Programming Language :: Python
Classifier: Programming Language :: Python :: 3
Requires-Python: >=3.9
Requires-Dist: aiohttp
